{
    "openapi": "3.0.0",
    "info": {
        "title": "JPI",
        "contact": {
            "email": "mschopdev@gmail.com"
        },
        "version": "1.0"
    },
    "paths": {
        "/Tenant/{tenantId}/Attribute/Product": {
            "get": {
                "description": "Fetch product attribute definitions",
                "operationId": "App\\Controller\\AttributeController::getAllProductAttributes",
                "responses": {
                    "200": {
                        "description": "All defined product attributes",
                        "content": {
                            "application/json": {
                                "schema": {
                                    "type": "array",
                                    "items": {
                                        "$ref": "#/components/schemas/Attribute"
                                    }
                                }
                            }
                        }
                    }
                }
            }
        },
        "/Tenant/{tenantId}/Attribute/Category": {
            "get": {
                "description": "Fetch product attribute definitions",
                "operationId": "App\\Controller\\AttributeController::getAllCategoryAttributes",
                "responses": {
                    "200": {
                        "description": "All defined product attributes",
                        "content": {
                            "application/json": {
                                "schema": {
                                    "type": "array",
                                    "items": {
                                        "$ref": "#/components/schemas/Attribute"
                                    }
                                }
                            }
                        }
                    }
                }
            }
        },
        "/": {
            "get": {
                "operationId": "App\\Controller\\IndexController::index",
                "responses": {
                    "200": {
                        "description": "Get status information"
                    }
                }
            }
        },
        "/Tenant/{tenantId}/Product/{productId}/Attribute": {
            "get": {
                "description": "Fetch all attribute values from product",
                "operationId": "App\\Controller\\ProductAttributeController::getAll",
                "responses": {
                    "200": {
                        "description": "Success",
                        "content": {
                            "application/json": {
                                "schema": {
                                    "type": "array",
                                    "items": {
                                        "$ref": "#/components/schemas/ProductAttribute"
                                    }
                                }
                            }
                        }
                    },
                    "404": {
                        "description": "Not Found"
                    },
                    "403": {
                        "description": "Forbidden"
                    }
                }
            }
        },
        "/Tenant/{tenantId}/Product/{productId}/BuyInterval": {
            "get": {
                "description": "Get the products buy interval settings",
                "operationId": "App\\Controller\\ProductBuyIntervalController::getAll",
                "parameters": [
                    {
                        "name": "tenantId",
                        "in": "path",
                        "required": true,
                        "schema": {
                            "type": "integer"
                        }
                    },
                    {
                        "name": "productId",
                        "in": "path",
                        "required": true,
                        "schema": {
                            "type": "integer"
                        }
                    }
                ],
                "responses": {
                    "200": {
                        "description": "Successful",
                        "content": {
                            "application/json": {
                                "schema": {
                                    "type": "array",
                                    "items": {
                                        "$ref": "#/components/schemas/ProductBuyInterval"
                                    }
                                }
                            }
                        }
                    },
                    "400": {
                        "description": "Bad Request"
                    },
                    "404": {
                        "description": "Product not found"
                    }
                }
            }
        },
        "/Tenant/{tenantId}/Product/{productId}": {
            "get": {
                "description": "Get a specific product",
                "operationId": "App\\Controller\\ProductController::getOne",
                "parameters": [
                    {
                        "name": "tenantId",
                        "in": "path",
                        "required": true,
                        "schema": {
                            "type": "integer"
                        }
                    },
                    {
                        "name": "productId",
                        "in": "path",
                        "required": true,
                        "schema": {
                            "type": "integer"
                        }
                    }
                ],
                "responses": {
                    "200": {
                        "description": "Successful",
                        "content": {
                            "application/json": {
                                "schema": {
                                    "$ref": "#/components/schemas/Product"
                                }
                            }
                        }
                    },
                    "404": {
                        "description": "Product not found"
                    }
                }
            }
        },
        "/Tenant/{tenantId}/Product/{productId}/Description": {
            "get": {
                "description": "Fetch all descriptions from a specific product",
                "operationId": "App\\Controller\\ProductDescriptionController::getAll",
                "parameters": [
                    {
                        "name": "tenantId",
                        "in": "path",
                        "required": true,
                        "schema": {
                            "type": "integer"
                        }
                    },
                    {
                        "name": "productId",
                        "in": "path",
                        "required": true,
                        "schema": {
                            "type": "integer"
                        }
                    }
                ],
                "responses": {
                    "200": {
                        "description": "Successful",
                        "content": {
                            "application/json": {
                                "schema": {
                                    "type": "array",
                                    "items": {
                                        "$ref": "#/components/schemas/ProductDescription"
                                    }
                                }
                            }
                        }
                    },
                    "400": {
                        "description": "Bad Request"
                    },
                    "404": {
                        "description": "Not Found"
                    }
                }
            }
        },
        "/Tenant": {
            "get": {
                "description": "Fetch all created tenants in JTL-Wawi installation.",
                "operationId": "App\\Controller\\TenantController::getAll",
                "responses": {
                    "200": {
                        "description": "Successfull operation",
                        "content": {
                            "application/json": {
                                "schema": {
                                    "type": "array",
                                    "items": {
                                        "$ref": "#/components/schemas/Tenant"
                                    }
                                }
                            }
                        }
                    }
                }
            }
        }
    },
    "components": {
        "schemas": {
            "Attribute": {
                "properties": {
                    "id": {
                        "type": "integer"
                    },
                    "isMultilingual": {
                        "type": "boolean"
                    },
                    "sort": {
                        "type": "integer"
                    },
                    "description": {
                        "type": "string"
                    },
                    "outputType": {
                        "type": "integer"
                    },
                    "isDefault": {
                        "type": "boolean"
                    },
                    "fieldTypeId": {
                        "type": "integer"
                    },
                    "regex": {
                        "type": "string"
                    },
                    "groupName": {
                        "type": "string"
                    },
                    "isReadOnly": {
                        "type": "boolean"
                    },
                    "translations": {
                        "type": "array",
                        "items": {
                            "$ref": "#/components/schemas/AttributeTranslation"
                        }
                    },
                    "shops": {
                        "type": "array",
                        "items": {
                            "$ref": "#/components/schemas/AttributeShop"
                        }
                    }
                },
                "type": "object"
            },
            "AttributeShop": {
                "properties": {
                    "shopId": {
                        "type": "integer"
                    }
                },
                "type": "object"
            },
            "AttributeTranslation": {
                "properties": {
                    "languageId": {
                        "type": "integer"
                    },
                    "name": {
                        "type": "string"
                    },
                    "valueList": {
                        "type": "array",
                        "items": {
                            "type": "string"
                        }
                    }
                },
                "type": "object"
            },
            "DeliveryAddress": {
                "properties": {
                    "id": {
                        "type": "integer"
                    },
                    "customerId": {
                        "type": "integer"
                    },
                    "company": {
                        "type": "string"
                    },
                    "salutation": {
                        "type": "string"
                    },
                    "title": {
                        "type": "string"
                    },
                    "firstName": {
                        "type": "string"
                    },
                    "name": {
                        "type": "string"
                    },
                    "street": {
                        "type": "string"
                    },
                    "postcode": {
                        "type": "string"
                    },
                    "city": {
                        "type": "string"
                    },
                    "country": {
                        "type": "string"
                    },
                    "phone": {
                        "type": "string"
                    },
                    "addition": {
                        "type": "string"
                    },
                    "addressAddition": {
                        "type": "string"
                    },
                    "postId": {
                        "type": "string"
                    },
                    "mobile": {
                        "type": "string"
                    },
                    "mail": {
                        "type": "string"
                    },
                    "fax": {
                        "type": "string"
                    },
                    "state": {
                        "type": "string"
                    },
                    "countryIsoCode": {
                        "type": "string"
                    }
                },
                "type": "object"
            },
            "InvoiceAddress": {
                "properties": {
                    "id": {
                        "type": "integer"
                    },
                    "customerId": {
                        "type": "integer"
                    },
                    "company": {
                        "type": "string"
                    },
                    "salutation": {
                        "type": "string"
                    },
                    "title": {
                        "type": "string"
                    },
                    "firstName": {
                        "type": "string"
                    },
                    "name": {
                        "type": "string"
                    },
                    "street": {
                        "type": "string"
                    },
                    "postcode": {
                        "type": "string"
                    },
                    "city": {
                        "type": "string"
                    },
                    "country": {
                        "type": "string"
                    },
                    "phone": {
                        "type": "string"
                    },
                    "addition": {
                        "type": "string"
                    },
                    "addressAddition": {
                        "type": "string"
                    },
                    "postId": {
                        "type": "string"
                    },
                    "mobile": {
                        "type": "string"
                    },
                    "mail": {
                        "type": "string"
                    },
                    "fax": {
                        "type": "string"
                    },
                    "state": {
                        "type": "string"
                    },
                    "countryIsoCode": {
                        "type": "string"
                    },
                    "customerNumber": {
                        "type": "string"
                    },
                    "attention": {
                        "type": "string"
                    }
                },
                "type": "object"
            },
            "Order": {
                "properties": {
                    "id": {
                        "type": "integer"
                    },
                    "invoiceId": {
                        "type": "integer"
                    },
                    "userId": {
                        "type": "integer"
                    },
                    "orderNumber": {
                        "type": "string"
                    },
                    "type": {
                        "type": "string"
                    },
                    "annotation": {
                        "type": "string"
                    },
                    "createdAt": {
                        "type": "string"
                    },
                    "dayTerm": {
                        "type": "integer"
                    },
                    "deliveryTypeId": {
                        "type": "integer"
                    },
                    "grossDeliveryCosts": {
                        "type": "string"
                    },
                    "discount": {
                        "type": "string"
                    },
                    "deliveryInfo": {
                        "type": "string"
                    },
                    "releasedForDeliveryAt": {
                        "type": "string"
                    },
                    "identCode": {
                        "type": "string"
                    },
                    "description": {
                        "type": "string"
                    },
                    "inet": {
                        "type": "string"
                    },
                    "deliveredAt": {
                        "type": "string"
                    },
                    "orderHint": {
                        "type": "integer"
                    },
                    "accountOfProceeds": {
                        "type": "string"
                    },
                    "currency": {
                        "type": "string"
                    },
                    "currencyFactor": {
                        "type": "string"
                    },
                    "shopId": {
                        "type": "integer"
                    },
                    "companyId": {
                        "type": "integer"
                    },
                    "logisticianId": {
                        "type": "integer"
                    },
                    "platform": {
                        "type": "integer"
                    },
                    "languageId": {
                        "type": "integer"
                    },
                    "voucherValue": {
                        "type": "string"
                    },
                    "printedAt": {
                        "type": "string"
                    },
                    "mailedAt": {
                        "type": "string"
                    },
                    "inetOrderNumber": {
                        "type": "string"
                    },
                    "paymentMethodId": {
                        "type": "integer"
                    },
                    "isIgl": {
                        "type": "boolean"
                    },
                    "isVatExempt": {
                        "type": "boolean"
                    },
                    "status": {
                        "type": "string"
                    },
                    "deliveryMailSentAt": {
                        "type": "string"
                    },
                    "paymentMailSentAt": {
                        "type": "string"
                    },
                    "userName": {
                        "type": "string"
                    },
                    "paymentReferenceLine": {
                        "type": "string"
                    },
                    "earlyPaymentDiscount": {
                        "type": "string"
                    },
                    "isCancelled": {
                        "type": "integer"
                    },
                    "moduleId": {
                        "type": "string"
                    },
                    "paymentType": {
                        "type": "integer"
                    },
                    "hasUpload": {
                        "type": "integer"
                    },
                    "additionalWeight": {
                        "type": "string"
                    },
                    "isDeliveredCompletely": {
                        "type": "boolean"
                    },
                    "payedAt": {
                        "type": "string"
                    },
                    "splitOrderId": {
                        "type": "integer"
                    },
                    "priority": {
                        "type": "integer"
                    },
                    "deliveryCountryIsoCode": {
                        "type": "string"
                    },
                    "vatNumber": {
                        "type": "string"
                    },
                    "isPremium": {
                        "type": "boolean"
                    },
                    "deliveryCountryCurrency": {
                        "type": "string"
                    },
                    "deliveryCountryCurrencyFactor": {
                        "type": "string"
                    },
                    "customerOrderNumber": {
                        "type": "string"
                    },
                    "isExtenalInvoice": {
                        "type": "boolean"
                    },
                    "campaign": {
                        "type": "string"
                    },
                    "campaignParam": {
                        "type": "string"
                    },
                    "campaignName": {
                        "type": "string"
                    },
                    "userAgent": {
                        "type": "string"
                    },
                    "referrer": {
                        "type": "string"
                    },
                    "maxDeliveryDays": {
                        "type": "integer"
                    },
                    "invoiceAddress": {
                        "$ref": "#/components/schemas/InvoiceAddress"
                    },
                    "deliveryAddress": {
                        "$ref": "#/components/schemas/DeliveryAddress"
                    }
                },
                "type": "object"
            },
            "Product": {
                "properties": {
                    "id": {
                        "type": "integer"
                    },
                    "sku": {
                        "type": "string"
                    },
                    "netPrice": {
                        "type": "string"
                    },
                    "rrp": {
                        "type": "string"
                    },
                    "note": {
                        "type": "string"
                    },
                    "isPriceList": {
                        "type": "boolean"
                    },
                    "isActive": {
                        "type": "boolean"
                    },
                    "stock": {
                        "type": "string"
                    },
                    "minOrderAmount": {
                        "type": "string"
                    },
                    "gtin": {
                        "type": "string"
                    },
                    "descriptions": {
                        "type": "array",
                        "items": {
                            "$ref": "#/components/schemas/ProductDescription"
                        }
                    },
                    "buyIntervals": {
                        "type": "array",
                        "items": {
                            "$ref": "#/components/schemas/ProductBuyInterval"
                        }
                    },
                    "attributes": {
                        "type": "array",
                        "items": {
                            "$ref": "#/components/schemas/ProductAttribute"
                        }
                    }
                },
                "type": "object"
            },
            "ProductAttribute": {
                "properties": {
                    "id": {
                        "type": "integer"
                    },
                    "attributeId": {
                        "type": "integer"
                    },
                    "shopId": {
                        "type": "integer"
                    },
                    "productId": {
                        "type": "integer"
                    },
                    "translations": {
                        "type": "array",
                        "items": {
                            "$ref": "#/components/schemas/ProductAttributeTranslation"
                        }
                    },
                    "attribute": {
                        "$ref": "#/components/schemas/Attribute"
                    }
                },
                "type": "object"
            },
            "ProductAttributeTranslation": {
                "properties": {
                    "productAttributeId": {
                        "type": "integer"
                    },
                    "languageId": {
                        "type": "integer"
                    },
                    "stringValue": {
                        "type": "string"
                    },
                    "dateValue": {
                        "type": "string"
                    },
                    "decimalValue": {
                        "type": "string"
                    },
                    "intValue": {
                        "type": "integer"
                    }
                },
                "type": "object"
            },
            "ProductBuyInterval": {
                "properties": {
                    "customerGroupId": {
                        "type": "integer"
                    },
                    "interval": {
                        "type": "string"
                    },
                    "minBuyAmount": {
                        "type": "string"
                    }
                },
                "type": "object"
            },
            "ProductDescription": {
                "properties": {
                    "languageId": {
                        "type": "integer"
                    },
                    "platformId": {
                        "type": "integer"
                    },
                    "shopId": {
                        "type": "integer"
                    },
                    "name": {
                        "type": "string"
                    },
                    "description": {
                        "type": "string"
                    },
                    "shopDescription": {
                        "type": "string"
                    },
                    "urlPath": {
                        "type": "string"
                    },
                    "metaDescription": {
                        "type": "string"
                    },
                    "metaTitle": {
                        "type": "string"
                    },
                    "metaKeywords": {
                        "type": "string"
                    }
                },
                "type": "object"
            },
            "Tenant": {
                "properties": {
                    "id": {
                        "type": "integer"
                    },
                    "name": {
                        "type": "string"
                    },
                    "dbName": {
                        "type": "string"
                    }
                },
                "type": "object"
            }
        }
    }
}